iab_tcf/__init__.py
iab_tcf/bits.py
iab_tcf/iab_tcf.py
iab_tcf/iab_tcf_v1.py
iab_tcf/iab_tcf_v2.py
iab_tcf/v2/__init__.py
iab_tcf/v2/non_core_segments.py
iab_tcf/v2/publisher_restriction.py
iab_tcf/v2/publisher_tc.py
tests/__init__.py
tests/conftest.py
tests/test_bits.py
tests/test_iab_tcf.py
tests/test_iab_tcf_v1.py
tests/test_iab_tcf_v2.py
iab_tcf_bitarray-0.2.3.dist-info/LICENSE
iab_tcf_bitarray-0.2.3.dist-info/METADATA
iab_tcf_bitarray-0.2.3.dist-info/WHEEL
iab_tcf_bitarray-0.2.3.dist-info/top_level.txt
iab_tcf_bitarray-0.2.3.dist-info/RECORD
