Metadata-Version: 2.1
Name: iab-tcf-bitarray
Version: 0.2.3
Summary: A Python implementation of the IAB consent strings (v1.1 and v2)
Home-page: https://github.com/gguridi/iab-tcf
Author: Gorka Guridi
Author-email: gorka.guridi@gmail.com
Classifier: Programming Language :: Python :: 3
Classifier: License :: OSI Approved :: MIT License
Classifier: Operating System :: OS Independent
Requires-Python: >=3.6
License-File: LICENSE
Requires-Dist: bitarray >=1.5.2
